{
  "project_info": {
    "project_number": "631866624337",
    "project_id": "gita-connect",
    "storage_bucket": "gita-connect.firebasestorage.app"
  },
  "client": [
    {
      "client_info": {
        "mobilesdk_app_id": "1:631866624337:android:26ed7300d264fed556ab70",
        "android_client_info": {
          "package_name": "com.gitaconnectin.app"
        }
      },
      "oauth_client": [
        {
          "client_id": "631866624337-o3s3je8287bgg51fu7ig923k0elad2hh.apps.googleusercontent.com",
          "client_type": 1,
          "android_info": {
            "package_name": "com.gitaconnectin.app",
            "certificate_hash": "3e747653e13120072b08362d3672bf7c6d5ee97e"
          }
        },
        {
          "client_id": "631866624337-kcep6ilovff2hl2c804404f27evdpsp1.apps.googleusercontent.com",
          "client_type": 3
        }
      ],
      "api_key": [
        {
          "current_key": "AIzaSyBD4F0XIju3WEwhCYOnMnMoY7E_BZ5R-Z4"
        }
      ],
      "services": {
        "appinvite_service": {
          "other_platform_oauth_client": [
            {
              "client_id": "631866624337-kcep6ilovff2hl2c804404f27evdpsp1.apps.googleusercontent.com",
              "client_type": 3
            },
            {
              "client_id": "631866624337-32lolvccl9os799k9n8k74kl0jl221bm.apps.googleusercontent.com",
              "client_type": 2,
              "ios_info": {
                "bundle_id": "com.gitaconnectin.app"
              }
            }
          ]
        }
      }
    }
  ],
  "configuration_version": "1"
}